{
    "id": 10325,
    "username": "daniel26",
    "name": "Nathan Carter",
    "email": "whiggins@hotmail.com",
    "birthdate": "1959-02-17",
    "phone": "+1-796-262-1619x4228",
    "keywords": [
        74,
        23,
        37,
        49,
        17,
        51
    ],
    "login locations": [
        [
            -122.043647,
            37.361716
        ]
    ],
    "relationships": {
        "158": 0.0281690140845,
        "355": 0.0145454545455,
        "4353": 0.01,
        "5084": 0.142857142857,
        "6356": 0.0333333333333,
        "8638": 0.08
    }
}