{
    "id": 156244,
    "username": "rodriguezheidi",
    "name": "Sandra Joyce",
    "email": "murillobrianna@yahoo.com",
    "birthdate": "1998-04-27",
    "phone": "755-729-8950x61107",
    "keywords": [
        24,
        4,
        39,
        45,
        3,
        39,
        68,
        45,
        1,
        65,
        48,
        22,
        1,
        71,
        1
    ],
    "login locations": [
        [
            -122.092964,
            37.398354
        ]
    ],
    "relationships": []
}