{
    "id": 158,
    "username": "dana78",
    "name": "Janet Bates",
    "email": "tylerhowe@hotmail.com",
    "birthdate": "1950-12-25",
    "phone": "001-721-489-3692x957",
    "keywords": [
        28,
        33,
        67,
        26,
        1,
        43,
        60
    ],
    "login locations": [
        [
            -122.081816,
            37.393549
        ]
    ],
    "relationships": {
        "93": 0.056,
        "8195": 0.105263157895,
        "4362": 0.0574712643678,
        "5103": 0.133333333333,
        "8638": 0.12,
        "10325": 0.0869565217391,
        "10326": 0.111111111111,
        "600": 0.0290909090909,
        "5084": 0.142857142857,
        "5087": 0.12,
        "355": 0.0181818181818,
        "7526": 0.03,
        "2415": 0.0512820512821,
        "6385": 0.0588235294118,
        "6356": 0.0166666666667,
        "5114": 0.2,
        "6398": 0.1
    }
}