{
    "id": 4093,
    "username": "hollyjackson",
    "name": "David Johnson",
    "email": "taylorbrandon@gmail.com",
    "birthdate": "1957-11-09",
    "phone": "+1-140-559-3499x193",
    "keywords": [
        55,
        57
    ],
    "login locations": [
        [
            -122.109922,
            37.424667
        ]
    ],
    "relationships": {
        "472": 0.0453074433657,
        "484": 0.056,
        "3572": 0.041975308642,
        "3585": 0.0453074433657,
        "3966": 0.01,
        "4178": 0.0219298245614,
        "70263": 0.0344827586207,
        "4905": 0.0652173913043,
        "4757": 0.0322580645161,
        "13262": 0.0511363636364
    }
}