{
    "id": 5291,
    "username": "troy75",
    "name": "Lucas Meadows",
    "email": "dawsonjoshua@gmail.com",
    "birthdate": "1924-03-04",
    "phone": "001-429-676-3843x925",
    "keywords": [
        25,
        49,
        42,
        61,
        58,
        1
    ],
    "login locations": [
        [
            -122.396841,
            37.773904
        ]
    ],
    "relationships": {
        "478": 0.01,
        "1454": 0.01,
        "1785": 0.01,
        "5287": 0.0201342281879,
        "5635": 0.01,
        "5638": 0.0217391304348,
        "5329": 0.0384615384615,
        "5346": 0.020202020202,
        "5353": 0.01,
        "8540": 0.014652014652
    }
}