{
    "id": 76345,
    "username": "cgilbert",
    "name": "John Jones",
    "email": "charles96@hotmail.com",
    "birthdate": "2020-07-06",
    "phone": "001-493-452-0181",
    "keywords": [
        68,
        21,
        58,
        20,
        16,
        45,
        36,
        71
    ],
    "login locations": [
        [
            -122.417931,
            37.739128
        ]
    ],
    "relationships": [
        [
            [
                5628,
                0.021686746988
            ],
            [
                5628,
                0.021686746988
            ]
        ]
    ]
}